README.md
setup.py
plenum_zmq_check.egg-info/PKG-INFO
plenum_zmq_check.egg-info/SOURCES.txt
plenum_zmq_check.egg-info/dependency_links.txt
plenum_zmq_check.egg-info/requires.txt
plenum_zmq_check.egg-info/top_level.txt
test_zmq/__init__.py
test_zmq/__version__.py
test_zmq/authenticator.py
test_zmq/client.py
test_zmq/server.py
test_zmq/util.py
test_zmq/zstack.py
test_zmq/crypto/__init__.py
test_zmq/crypto/encoding.py
test_zmq/crypto/nacl_wrappers.py
test_zmq/crypto/signer.py
test_zmq/crypto/util.py