Metadata-Version: 1.2
Name: plenum-zmq-check
Version: 1.0.0
Summary: Tool for checking ZMQ connection
Home-page: https://github.com/hyperledger/indy-plenum/tree/master/scripts/test_zmq
Author: Hyperledger
Author-email: hyperledger-indy@lists.hyperledger.org
Maintainer: Hyperledger
License: Apache 2.0
Keywords: zmq tcp check connection
Platform: UNKNOWN
